lazy_core/__init__.py
lazy_core/api.py
lazy_core/app.py
lazy_core/encoder.py
lazy_core/middleware.py
lazy_core/module.py
lazy_core/py.typed
lazy_core-0.1.2.dist-info/LICENSE
lazy_core-0.1.2.dist-info/METADATA
lazy_core-0.1.2.dist-info/WHEEL
lazy_core-0.1.2.dist-info/RECORD
