Metadata-Version: 2.3
Name: lazy-core
Version: 0.1.2
Summary: Lazy-Core is the core module of the Lazy framework family.
License: MIT License
Author: wrl96
Author-email: ruilin.wang96@gmail.com
Requires-Python: >=3.9
Classifier: License :: Other/Proprietary License
Classifier: Programming Language :: Python :: 3
Classifier: Programming Language :: Python :: 3.9
Classifier: Programming Language :: Python :: 3.10
Classifier: Programming Language :: Python :: 3.11
Classifier: Programming Language :: Python :: 3.12
Classifier: Programming Language :: Python :: 3.13
Requires-Dist: pydantic (>=2.11.7,<3.0.0)
